evaluators/__init__.py
evaluators/_abc.py
evaluators/_shm.py
evaluators/_types.py
evaluators/_utils.py
evaluators/base_evaluator.py
evaluators/depth.py
evaluators/dvps.py
evaluators/panseg.py
evaluators/step.py
evaluators-1.0.3.dist-info/LICENSE
evaluators-1.0.3.dist-info/METADATA
evaluators-1.0.3.dist-info/WHEEL
evaluators-1.0.3.dist-info/top_level.txt
evaluators-1.0.3.dist-info/RECORD
